snippets_menu_magic/__init__.py
snippets_menu_magic/magic.json
snippets_menu_magic/menu.json
snippets_menu_magic/nb_register.py
snippets_menu_magic/snippets.py
snippets_menu_magic-0.2.2.dist-info/LICENSE
snippets_menu_magic-0.2.2.dist-info/WHEEL
snippets_menu_magic-0.2.2.dist-info/METADATA
snippets_menu_magic-0.2.2.dist-info/RECORD
