Metadata-Version: 2.1
Name: snippets_menu_magic
Version: 0.2.2
Summary: Snippets menu magic
Home-page: https://github.com/diramazioni/snippets_menu_magic
License: UNKNOWN
Keywords: ipython jupyter snippet menu magic
Author: Eli Spizzichino
Author-email: scrivi@gmail.com
Classifier: Intended Audience :: Developers
Classifier: Framework :: IPython
Classifier: License :: OSI Approved :: Apache Software License
Classifier: Programming Language :: Python :: 3
Classifier: Topic :: Software Development :: Libraries :: Python Modules
Requires-Dist: jupyter_contrib_nbextensions >= 0.5.0
Requires-Dist: dpath >=1.4.2
Provides-Extra: .none
